{
  "date": "2026-07-23",
  "total": 21,
  "targetCount": 6,
  "sources": {
    "mss": {
      "id": "mss",
      "name": "중소벤처기업부",
      "icon": "🏛️",
      "color": "#1a4fa0",
      "count": 100,
      "targetCount": 21,
      "items": [
        {
          "id": "mss_1068742",
          "source": "mss",
          "title": "「민관협력 오픈이노베이션 지원」 2026년 제2차 방산 스타트업 챌린지(모두의 챌린지–방산) 수요기업 협업 과제 모집공고",
          "url": "https://www.mss.go.kr/site/smba/ex/bbs/View.do?cbIdx=310&bcIdx=1068742",
          "date": "2026-06-22",
          "org": "신산업기술창업과",
          "region": "전국",
          "category": "사업화",
          "isTarget": false,
          "detail": {
            "period": "2026-06-02 ~ 2026-06-22",
            "eligibility": "",
            "content": "방산 분야 신기술 적용 수요가 있는 군 및 수요기업과 창업기업 간 협력을 통한 동반 성장 지원을 위해<br />\n「민관협력 오픈이노베이션 지원」 2026년 제2차 방산 스타트업 챌린지(모두의 챌린지&ndash;방산)<br />\n수요기업 협업 과제를 다음과 같이 모집합니다.\n<div data-hjsonver=\"1.0\" data-jsonlen=\"9257\" id=\"hwpEditorBoardContent\">&nbsp;</div>\n□ 사업목적 : 방산 분야 신기술 적용 수요가 있는 군 및 수요기업과 창업기업 간 오픈이노베이션 활성화 및 동반",
            "amount": ""
          }
        },
        {
          "id": "mss_1068716",
          "source": "mss",
          "title": "2026년도 2차 대중소기업동반진출지원사업 주관기업 모집 공고",
          "url": "https://www.mss.go.kr/site/smba/ex/bbs/View.do?cbIdx=310&bcIdx=1068716",
          "date": "2026-06-26",
          "org": "글로벌성장정책과",
          "region": "전국",
          "category": "사업화",
          "isTarget": false,
          "detail": {
            "period": "2026-06-01 ~ 2026-06-26",
            "eligibility": "",
            "content": "<br />\n2026년도 2차 대중소기업동반진출지원사업 주관기업 모집을 붙임과 같이 공고합니다.",
            "amount": ""
          }
        },
        {
          "id": "mss_1068484",
          "source": "mss",
          "title": "『AI+ OpenData 챌린지』 참여기업 모집 수정 공고",
          "url": "https://www.mss.go.kr/site/smba/ex/bbs/View.do?cbIdx=310&bcIdx=1068484",
          "date": "",
          "org": "정보화담당관",
          "region": "전국",
          "category": "사업화",
          "isTarget": false,
          "detail": {
            "period": "",
            "eligibility": "",
            "content": "AI+ OpenData 챌린지 (공고 제2026-327호, &#39;26.5.11)를 다음과 같이 수정하여 공고합니다.<br />\n<br />\n&nbsp;ㅇ 신청제외 대상, 유의사항 내용 추가<br />\n<br />\n자세한 내용은 공고문을 첨부하여 주시기 바랍니다.",
            "amount": ""
          }
        },
        {
          "id": "mss_1068434",
          "source": "mss",
          "title": "「2026년 민관협력 오픈이노베이션 지원」 제2차 수요기업‧기관 협업 과제 및 프로그램 모집공고",
          "url": "https://www.mss.go.kr/site/smba/ex/bbs/View.do?cbIdx=310&bcIdx=1068434",
          "date": "2026-06-09",
          "org": "신산업기술창업과",
          "region": "전국",
          "category": "사업화",
          "isTarget": false,
          "detail": {
            "period": "2026-05-20 ~ 2026-06-09",
            "eligibility": "",
            "content": "스타트업과 수요기업(대&middot;중견기업&middot;공공기관 등)간 협력을 통한 동반성장 지원을 위해<br />\n「2026년 민관협력 오픈이노베이션 지원」사업에 참여할 수요기업&middot;기관의 협업 과제(전략과제 해결형) 및 협업 프로그램(민간 선별추천형)을 다음과 같이 모집합니다.<br />\n<br />\n□ 사업목적 : 수요기업&middot;스타트업 간 오픈이노베이션 정보 제공 및 중개 플랫폼 등을 통해 기업 간 상생협력 및 스타트업 성장 촉진<br />\n□ 모집대상 : 창업기업과 협력을 희망하는 수요기업(대&middot",
            "amount": ""
          }
        },
        {
          "id": "mss_1068102",
          "source": "mss",
          "title": "『AI+ OpenData 챌린지』 참여기업 모집공고",
          "url": "https://www.mss.go.kr/site/smba/ex/bbs/View.do?cbIdx=310&bcIdx=1068102",
          "date": "2026-06-05",
          "org": "정보화담당관",
          "region": "전국",
          "category": "사업화",
          "isTarget": false,
          "detail": {
            "period": "2026-05-11 ~ 2026-06-05",
            "eligibility": "",
            "content": "공공기관의 현안 해결을 위해 기관이 실제 사용하는 현장데이터를 AI 스타트업에 공개하고, 혁신적인 AI 솔루션 발굴을 지원하는&nbsp;「AI+ OpenData 챌린지」참여기업을 아래와 같이 모집합니다.<br />\n<br />\n<br />\n□ 사업목적 : 공공기관의 현안 해결을 위해 기관이 실제 사용하는 현장 데이터를 AI 스타트업에 공개하고, 혁신적인 AI 솔루션 발굴<br />\n&nbsp;<br />\n□ 주 최 : 중소벤처기업부<br />\n&nbsp;<br />\n□ 주 관 : 중소벤처기업진흥공단<br />\n&nbsp;<br />",
            "amount": ""
          }
        },
        {
          "id": "mss_1068080",
          "source": "mss",
          "title": "2026년 소공인 판로개척지원사업 모집 공고",
          "url": "https://www.mss.go.kr/site/smba/ex/bbs/View.do?cbIdx=310&bcIdx=1068080",
          "date": "2026-06-05",
          "org": "소공인성장촉진단",
          "region": "전국",
          "category": "판로/마케팅",
          "isTarget": false,
          "detail": {
            "period": "2026-05-08 ~ 2026-06-05",
            "eligibility": "",
            "content": "<br />\n성장잠재력을 갖춘 유망 소공인의 육성을 위한「2026년 소공인 판로개척지원사업」협업기관 및 소공인 모집을 아래와 같이 공고하오니 참여를 희망하는 기업은 많은 신청 바랍니다.<br />\n<br />\n&lt; 사업 신청 기간 &gt;<br />\n민간협업형 협업기관&nbsp; &#39;26.5.8.(금)~5.22(금) 18시까지<br />\n민간협업형 참여 소공인&nbsp; &#39;26.5.8.(금)~6.5.(금) 18시까지<br />\n개별형 참여 소공인 &#39;26.5.18.(월)~6.5.(금) 18시까지&nbsp;&nb",
            "amount": ""
          }
        },
        {
          "id": "mss_1068076",
          "source": "mss",
          "title": "2026년 소상공인 생활문화 혁신지원 사업 주관기관 모집 공고",
          "url": "https://www.mss.go.kr/site/smba/ex/bbs/View.do?cbIdx=310&bcIdx=1068076",
          "date": "2026-05-26",
          "org": "소상공인정책과",
          "region": "전국",
          "category": "사업화",
          "isTarget": false,
          "detail": {
            "period": "2026-05-08 ~ 2026-05-26",
            "eligibility": "",
            "content": "지역 소상공인의 제품&middot;서비스 개선을 통한 부가가치 제고와 지역기반 성장 촉진을 위한<br />\n<br />\n「 2026년 소상공인 생활문화 혁신지원」 사업에 참여할 주관기관을 붙임과 같이 모집합니다.",
            "amount": ""
          }
        },
        {
          "id": "mss_1067945",
          "source": "mss",
          "title": "2026년 소공인 클린제조환경조성사업 모집 공고",
          "url": "https://www.mss.go.kr/site/smba/ex/bbs/View.do?cbIdx=310&bcIdx=1067945",
          "date": "2026-06-02",
          "org": "소공인성장촉진단",
          "region": "전국",
          "category": "사업화",
          "isTarget": false,
          "detail": {
            "period": "2026-04-30 ~ 2026-06-02",
            "eligibility": "",
            "content": "<br />\n소공인 작업장의 안전사고 예방 및 에너지효율개선 지원을 목적으로 추진하는「2026년 소공인 클린제조환경조성」사업을 다음과 같이 공고하오니 많은 관심과 참여바랍니다.\n<div data-hjsonver=\"1.0\" data-jsonlen=\"7619\" id=\"hwpEditorBoardContent\">&nbsp;</div>",
            "amount": ""
          }
        },
        {
          "id": "mss_1067942",
          "source": "mss",
          "title": "2026년 소공인 스마트제조지원사업 모집 공고",
          "url": "https://www.mss.go.kr/site/smba/ex/bbs/View.do?cbIdx=310&bcIdx=1067942",
          "date": "2026-06-02",
          "org": "소공인성장촉진단",
          "region": "전국",
          "category": "사업화",
          "isTarget": false,
          "detail": {
            "period": "2026-05-18 ~ 2026-06-02",
            "eligibility": "",
            "content": "<br />\n소공인의 제조 경쟁력 강화 및 디지털전환을 위해 ｢소공인 스마트 제조지원사업｣을 다음과 같이 공고하오니 참여를 희망하는 소공인의 많은 신청 바랍니다.\n<div data-hjsonver=\"1.0\" data-jsonlen=\"10580\" id=\"hwpEditorBoardContent\">&nbsp;</div>",
            "amount": ""
          }
        },
        {
          "id": "mss_1067590",
          "source": "mss",
          "title": "올해의 K-스타트업 2026  AI리그 참여기업 모집 공고",
          "url": "https://www.mss.go.kr/site/smba/ex/bbs/View.do?cbIdx=310&bcIdx=1067590",
          "date": "",
          "org": "신산업기술창업과",
          "region": "전국",
          "category": "사업화",
          "isTarget": true,
          "detail": {
            "period": "",
            "eligibility": "",
            "content": "올해의 K-스타트업 2026 &nbsp;AI리그 참여기업 모집 공고를 붙임과 같이 게시합니다.&nbsp;",
            "amount": ""
          }
        },
        {
          "id": "mss_1067487",
          "source": "mss",
          "title": "2026년도 중소기업 정책자금 융자계획 변경공고",
          "url": "https://www.mss.go.kr/site/smba/ex/bbs/View.do?cbIdx=310&bcIdx=1067487",
          "date": "",
          "org": "기업금융과",
          "region": "전국",
          "category": "자금지원",
          "isTarget": true,
          "detail": {
            "period": "",
            "eligibility": "",
            "content": "중소벤처기업부 공고 제2026-281호<br />\n<br />\n중소기업진흥에 관한 법률 제66조 및 제67조에 따른 &quot;2026년도 중소기업 정책자금 융자계획&quot;을 다음과 같이 변경공고합니다.<br />\n&nbsp;<br />\n&lt;주요 변경사항&gt;<br />\n1. 추가경정예산(&#39;추경&#39;) 확정에 따른 중소기업 정책자금 변경사항(증액) 반영<br />\n&nbsp; -&nbsp;해당자금 : 긴급경영안정자금, 신시장진출지원자금(수출기업 글로벌화), 혁신창업사업화자금(창업기반지원),&nbsp; 재도약지원자",
            "amount": ""
          }
        },
        {
          "id": "mss_1067475",
          "source": "mss",
          "title": "2026년 중소기업 혁신바우처(채용지원) 사업 지원계획 공고",
          "url": "https://www.mss.go.kr/site/smba/ex/bbs/View.do?cbIdx=310&bcIdx=1067475",
          "date": "2026-05-06",
          "org": "지역혁신정책과",
          "region": "전국",
          "category": "사업화",
          "isTarget": false,
          "detail": {
            "period": "2026-04-20 ~ 2026-05-06",
            "eligibility": "",
            "content": "중소벤처기업부 공고 제2026-280호<br />\n2026년 중소기업 혁신바우처(채용지원) 사업 지원계획을 붙임과 같이 공고합니다.<br />\n<br />\n<br />\n&nbsp;* 세부내용 및 지역별 공고는 혁신플랫폼(mssmiv.com)에서 확인 가능",
            "amount": ""
          }
        },
        {
          "id": "mss_1067461",
          "source": "mss",
          "title": "2026년 대한민국 소상공인 대회 유공자 포상 공고",
          "url": "https://www.mss.go.kr/site/smba/ex/bbs/View.do?cbIdx=310&bcIdx=1067461",
          "date": "2026-05-29",
          "org": "소상공인정책과",
          "region": "전국",
          "category": "사업화",
          "isTarget": false,
          "detail": {
            "period": "2026-04-20 ~ 2026-05-29",
            "eligibility": "",
            "content": "매년 11.5일 소상공인의 날을 기념하는 대한민국 소상공인대회에서 포상(훈포장 등 정부포상 포함)을 수여하기 위한<br />\n<br />\n소상공인 유공자 포상 후보자를 붙임과 같이 5.29일까지 공고하오니 많이 신청하여 주시기 바랍니다.<br />\n<br />\n신청 연락처(13페이지)는<br />\n<br />\n소상공인시장진흥공단은 각 지역센터, 소상공인연합회는 070-4944-1943, 각 지방중소벤처기업청입니다.<br />\n<br />\n<br />\n<br />\n&nbsp;",
            "amount": ""
          }
        }
      ]
    },
    "kstartup": {
      "id": "kstartup",
      "name": "K-Startup",
      "icon": "🚀",
      "color": "#e8360e",
      "count": 50,
      "targetCount": 36,
      "items": [
        {
          "id": "kstartup_178650",
          "source": "kstartup",
          "title": "2026-9회 호남권 엔젤투자 피칭룸 in 전남광주 참가기업 모집 안내",
          "url": "https://www.k-startup.go.kr/web/contents/bizpbanc-ongoing.do?schM=view&pbancSn=178650",
          "date": "2026-08-03",
          "org": "한국엔젤투자협회 호남권 엔젤투자허브",
          "region": "광주",
          "category": "사업화",
          "isTarget": false,
          "detail": {
            "period": "2026.07.22(수) 00:00 ~ 2026.08.03(월) 23:59 까지",
            "eligibility": "",
            "content": "투자유치 희망기업에 대한 사업계획서 검토 및 투자 연계를 위한 투자상담회 진행 ◦ (상담회) 투자자(1) : 기업(2) 매칭하여 기업당 1시간 이내 상담회 진행- 호남권 엔젤투자 피칭룸 선착순 접수 후, 선정기업 대상 상담위원 매칭하여 상담회 진행- 투자유치 가능성 진단 및 기업별 투자유치 방법 제안, 사업 아이템의 기술성 및 시장성 등에 대한 항목별 평가- 상담회 참여기업 중 투자유치 가능성이 높은 기업을 대상으로 협회 IR행사 등 연계 추진",
            "amount": ""
          }
        },
        {
          "id": "kstartup_178645",
          "source": "kstartup",
          "title": "KAIST 딥테크 유망랩 라운드테이블 ",
          "url": "https://www.k-startup.go.kr/web/contents/bizpbanc-ongoing.do?schM=view&pbancSn=178645",
          "date": "2026-08-07",
          "org": "(주)아이비유",
          "region": "전국",
          "category": "사업화",
          "isTarget": false,
          "detail": {
            "period": "2026.07.23(목) 09:00 ~ 2026.08.07(금) 18:00 까지",
            "eligibility": "",
            "content": "지원내용 ○ 1:1 기술 매칭 상담○ 공동 R&D 및 사업화 협의○ 신사업 협력 연계 지원",
            "amount": ""
          }
        },
        {
          "id": "kstartup_178640",
          "source": "kstartup",
          "title": "일본 후쿠오카 진출 지원 Plug in: Fukuoka #13 참가 스타트업 모집 공고(~ 7/31 18:00)",
          "url": "https://www.k-startup.go.kr/web/contents/bizpbanc-ongoing.do?schM=view&pbancSn=178640",
          "date": "2026-07-31",
          "org": "(재)부산창조경제혁신센터 대표이사",
          "region": "부산",
          "category": "사업화",
          "isTarget": true,
          "detail": {
            "period": "2026.07.21(화) 00:00 ~ 2026.07.31(금) 18:00 까지",
            "eligibility": "",
            "content": "항공료 실비 지원, RAMEN TECH 2026 부스 참여, 현지 피칭·네트워킹·비즈니스 밋업 등 Plug in : Fukuoka #13 연계 프로그램 참여 지원 · 기업당 1인, 최대 30만원 한도 내 항공료 실비 지원· RAMEN TECH 2026 내 참여기업 부스 운영 지원· BCCEI × Fukuoka Jisho 메인 프로그램 참여 등※공고문 참조",
            "amount": ""
          }
        },
        {
          "id": "kstartup_178639",
          "source": "kstartup",
          "title": "26년 국토교통 창업지원센터 입주기업 추가 모집공고",
          "url": "https://www.k-startup.go.kr/web/contents/bizpbanc-ongoing.do?schM=view&pbancSn=178639",
          "date": "2026-08-04",
          "org": "국토교통과학기술진흥원",
          "region": "전국",
          "category": "시설제공",
          "isTarget": true,
          "detail": {
            "period": "2026.07.21(화) 14:00 ~ 2026.08.04(화) 18:00 까지",
            "eligibility": "",
            "content": "국토교통 창업지원센터 지원내용 - 공유형 사무공간, 회의실 등 공간 무상제공- 상주 엑셀러레이터를 통한 창업기획 프로그램 제공",
            "amount": ""
          }
        },
        {
          "id": "kstartup_178637",
          "source": "kstartup",
          "title": "관악 라이브커머스 지원 참여기업 모집",
          "url": "https://www.k-startup.go.kr/web/contents/bizpbanc-ongoing.do?schM=view&pbancSn=178637",
          "date": "2026-08-16",
          "org": "관악구청",
          "region": "전국",
          "category": "사업화",
          "isTarget": false,
          "detail": {
            "period": "2026.07.21(화) 00:00 ~ 2026.08.16(일) 23:59 까지",
            "eligibility": "",
            "content": "라이브커머스 방송 촬영 지원, 라이브 방송 송출 지원 라이브커머스 방송 촬영 지원, 라이브 방송 송출 지원, 쇼호스트 지원",
            "amount": ""
          }
        },
        {
          "id": "kstartup_178636",
          "source": "kstartup",
          "title": "2026년 WEROUND 공유형 공간 신규 입주기업 상시 모집 ",
          "url": "https://www.k-startup.go.kr/web/contents/bizpbanc-ongoing.do?schM=view&pbancSn=178636",
          "date": "2026-08-07",
          "org": "서강대학교 판교캠퍼스사업단",
          "region": "전국",
          "category": "시설제공",
          "isTarget": false,
          "detail": {
            "period": "2026.07.22(수) 09:00 ~ 2026.08.07(금) 16:00 까지",
            "eligibility": "",
            "content": "전용 사무공간 및 인프라 제공 - 기본 사무기기(책상 및 의자) 및 전용 사무공간(좌석) 지원 (단, 기본 제공 사무기기 외 추가 지원 없음)- 회의실, 교육장, 휴게공간, 구내식당 및 편의시설 인프라 제공 임대료 전액 무상 지원(고정관리비 제외) 대·중견기업과의 협업 기회 - 모트렉스(주), ㈜이녹스첨단소재, 에스트래픽(주), 와이엠씨(주) 등과의 협업 기회 제공 스타트업 지원 기관과의 연계 지원 - 스타트업 육성 프로그램을 통한 전문기관인 회계법인, 액셀러레이터, 투자기관 등과의 연계 지원 네트워킹, 세미나 등 다양한 교류 기회",
            "amount": ""
          }
        },
        {
          "id": "kstartup_178627",
          "source": "kstartup",
          "title": "[무료] AI 콘텐츠 마케터/1인 마케팅 에이전시 창업가 육성과정",
          "url": "https://www.k-startup.go.kr/web/contents/bizpbanc-ongoing.do?schM=view&pbancSn=178627",
          "date": "2026-08-19",
          "org": "(주)메타코드에이치",
          "region": "전국",
          "category": "판로/마케팅",
          "isTarget": true,
          "detail": {
            "period": "2026.07.21(화) 10:00 ~ 2026.08.19(수) 18:00 까지",
            "eligibility": "",
            "content": "",
            "amount": ""
          }
        },
        {
          "id": "kstartup_178625",
          "source": "kstartup",
          "title": "[무료 웨비나] 글로벌 시장을 위한 AI 마이크로 서비스 제작 실전",
          "url": "https://www.k-startup.go.kr/web/contents/bizpbanc-ongoing.do?schM=view&pbancSn=178625",
          "date": "2026-07-30",
          "org": "The Bridge Circle (TBC)",
          "region": "전국",
          "category": "글로벌",
          "isTarget": true,
          "detail": {
            "period": "2026.07.21(화) 00:00 ~ 2026.07.30(목) 00:00 까지",
            "eligibility": "",
            "content": "",
            "amount": ""
          }
        }
      ]
    }
  },
  "todayDeadline": [
    {
      "id": "mss_1069454",
      "source": "mss",
      "title": "K-뷰티 사우디 진출 지원사업 참여기업 모집",
      "url": "https://www.mss.go.kr/site/smba/ex/bbs/View.do?cbIdx=310&bcIdx=1069454",
      "date": "2026-07-23",
      "org": "글로벌성장정책과",
      "region": "전국",
      "category": "사업화",
      "isTarget": false,
      "detail": {
        "period": "2026-06-29 ~ 2026-07-23",
        "eligibility": "",
        "content": "<br />\n중소벤처기업부와 주사우디아라비아왕국 대한민국대사관은 K-뷰티 기업의 사우디 진출을 지원하고자 붙임과 같이 &lsquo;K-뷰티 사우디 진출 지원사업&rsquo;을 추진하오니 역량 있는 기업들의 많은 참여 바랍니다.<br />\n<br />\n&nbsp;* 지원사업 사전설명회 :&nbsp;&lsquo;26.7.2(목) 14:00~15:30, 스타트업브랜치 피칭센터(서울시 강남구 영동대로 513(코엑스 2층))\n<div data-hjsonver=\"1.0\" data-jsonlen=\"10567\" id=\"hwpEditorBoardC",
        "amount": ""
      }
    }
  ]
}